didadata/__init__.py
didadata/admin.py
didadata/api.py
didadata/apps.py
didadata/exceptions.py
didadata/filters.py
didadata/models.py
didadata/serializers.py
didadata/urls.py
didadata/viewsets.py
didadata/locale/de/LC_MESSAGES/django.mo
didadata/locale/de/LC_MESSAGES/django.po
didadata/migrations/0001_initial.py
didadata/migrations/0002_auto_20151201_1939.py
didadata/migrations/0003_auto_20160311_2321.py
didadata/migrations/__init__.py
django_didadata-1.0.0.dist-info/LICENSE.rst
django_didadata-1.0.0.dist-info/METADATA
django_didadata-1.0.0.dist-info/WHEEL
django_didadata-1.0.0.dist-info/top_level.txt
django_didadata-1.0.0.dist-info/RECORD
