Metadata-Version: 2.1
Name: django-didadata
Version: 1.0.0
Summary: A Django app to collect numeric data.
Home-page: https://github.com/stephrdev/django-didadata/
Author: Stephan Jaekel, Benjamin Banduhn
Author-email: steph@rdev.info
License: BSD
Project-URL: Bug Reports, https://github.com/stephrdev/django-didadata/issues
Project-URL: Source, https://github.com/stephrdev/django-didadata
Keywords: django didadata
Platform: UNKNOWN
Classifier: Environment :: Web Environment
Classifier: Framework :: Django
Classifier: Intended Audience :: Developers
Classifier: License :: OSI Approved :: BSD License
Classifier: Programming Language :: Python :: 3
Classifier: Programming Language :: Python :: 3.6
Classifier: Programming Language :: Python :: 3.7
Classifier: Programming Language :: Python :: 3.8
Classifier: Programming Language :: Python :: 3.9
Requires-Dist: Django (>=2.2)
Requires-Dist: djangorestframework (>=3.12.1)
Requires-Dist: django-filter (>=2.4.0)
Provides-Extra: dev
Requires-Dist: pytest ; extra == 'dev'
Requires-Dist: pytest-black ; extra == 'dev'
Requires-Dist: pytest-isort ; extra == 'dev'
Requires-Dist: pytest-django ; extra == 'dev'
Requires-Dist: pytest-cov ; extra == 'dev'
Requires-Dist: pytest-flake8 ; extra == 'dev'
Requires-Dist: sphinx ; extra == 'dev'
Requires-Dist: sphinx-rtd-theme ; extra == 'dev'
Requires-Dist: factory-boy ; extra == 'dev'
